Workbook
Name Data_EixoX: OFFSET(AUXILIAR!$G$2,0,0,APP_INVEST!$D$42*12+1,1)
Name inflação_mensal: APP_INVEST!$D$24
Name Linha_Nominal_RE: OFFSET(AUXILIAR!$H$2,0,0,APP_INVEST!$D$42*12+1,1)
Name Linha_Nominal_SR: OFFSET(AUXILIAR!$J$2,0,0,APP_INVEST!$D$42*12+1,1)
Name Linha_Real_RE: OFFSET(AUXILIAR!$I$2,0,0,APP_INVEST!$D$42*12+1,1)
Name Linha_Real_SR: OFFSET(AUXILIAR!$K$2,0,0,APP_INVEST!$D$42*12+1,1)
Name Salario: APP_INVEST!$D$15
Name taxa_nominal: APP_INVEST!$D$23
Name taxa_real: APP_INVEST!$D$25
Name Taxa_rendimento: APP_INVEST!#REF!

Sheet APP_INVEST
B14: PERSONALIZAÇÃO
B15: Salário | D15: 4500
B16: Escolha a porcentagem para investir | D16: 0.2
B17: Quantos anos investir? | D17: 7
B18: Inflação média anual | D18: 0.04
B19: Perfil de investidor | D19: Moderado
B20: Reinvestir dividendos? | D20: Sim
B22: Sugestão de aporte | D22: =$D$15*$D$16 -> 900
B23: Taxa nominal mensal | D23: {=SUMPRODUCT((AUXILIAR!$B$2:$B$19=D19) * (AUXILIAR!$D$2:$D$19) * (AUXILIAR!$E$2:$E$19))} -> 0.009425
B24: Inflação estimada mensal | D24: =(1 + D18)^(1/12) - 1 -> 0.0032737398
B25: TAXA REAL MENSAL | D25: =((1 + D23) / (1 + D24)) - 1 -> 0.0061311883
B27: INVESTIMENTO MENSAL
B28: Aporte mensal estimado | D28: =$D$22 -> 900
B29: Tempo de investimento (anos) | D29: =D17 -> 7
B30: Patrimônio nominal | D30: =IF(D20="Sim", FV(D23, D17*12, -(D15*D16)), (D15*D16) * (D17*12)) -> 114491.2
B31: Patrimônio real - descontado inflação | D31: =IF(D20="Sim", FV(D25, D17*12, -(D15*D16)), ((D15*D16) * (D17*12)) / (1+D18)^D17) -> 98502.573
B32: Dividendos mensais | D32: =D30 * D23 -> 1079.0796
B34: CENÁRIOS
B35: Tempo | C35: Patrimônio Nominal | D35: Dividendos
A36: 2 | B36: Em 2 anos | C36: =-FV($D$23,$A36*12,$D$22) -> 24111.302 | D36: =C36*$D$23 -> 227.24902
A37: 5 | B37: Em 5 anos | C37: =-FV($D$23,$A37*12,$D$22) -> 72159.664 | D37: =C37*$D$23 -> 680.10483
A38: 10 | B38: Em 10 anos | C38: =-FV($D$23,$A38*12,$D$22) -> 198848.37 | D38: =C38*$D$23 -> 1874.1459
A39: 15 | B39: Em 15 anos | C39: =-FV($D$23,$A39*12,$D$22) -> 421272.18 | D39: =C39*$D$23 -> 3970.4903
A40: 20 | B40: Em 20 anos | C40: =-FV($D$23,$A40*12,$D$22) -> 811775.45 | D40: =C40*$D$23 -> 7650.9836
A41: 30 | B41: Em 30 anos | C41: =-FV($D$23,$A41*12,$D$22) -> 2701052.3 | D41: =C41*$D$23 -> 25457.417
B42: Visualizar no Gráfico (Anos): | D42: 7
B61: CARTEIRA RECOMENDADA
B62: Tipo de FII | C62: Percentual sugerido | D62: Valores
B63: PAPEL | C63: =VLOOKUP($D$19&"-"&$B63,AUXILIAR!A1:D19,4,) -> 0.32 | D63: =$D$28*$C63 -> 288
B64: TIJOLO | C64: =VLOOKUP($D$19&"-"&$B64,AUXILIAR!A2:D20,4,) -> 0.35 | D64: =$D$28*$C64 -> 315
B65: HÍBRIDOS | C65: =VLOOKUP($D$19&"-"&$B65,AUXILIAR!A3:D21,4,) -> 0.08 | D65: =$D$28*$C65 -> 72
B66: FOFs | C66: =VLOOKUP($D$19&"-"&$B66,AUXILIAR!A4:D22,4,) -> 0.05 | D66: =$D$28*$C66 -> 45
B67: DESENVOLVIMENTO | C67: =VLOOKUP($D$19&"-"&$B67,AUXILIAR!A5:D23,4,) -> 0.1 | D67: =$D$28*$C67 -> 90
B68: HOTELARIAS | C68: =VLOOKUP($D$19&"-"&$B68,AUXILIAR!A6:D24,4,) -> 0.1 | D68: =$D$28*$C68 -> 90
B69: Total | C69: =SUM(C63:C68) -> 1 | D69: =SUM(D63:D68) -> 900

Sheet AUXILIAR
A1: CHAVE | B1: PERFIL | C1: TIPO FII | D1: % DO APORTE | E1: YIELD ESTIMADO | G1: Mês | H1: Nominal (reinvest) | I1: Real (reinvest) | J1: Nominal (sem reinvest) | K1: Real (sem reinvest)
A2: =$B2&"-"&$C2 -> Conservador-PAPEL | B2: Conservador | C2: PAPEL | D2: 0.3 | E2: 0.011 | G2: 0 | H2: 0 | I2: 0 | J2: 0 | K2: 0
A3: =$B3&"-"&$C3 -> Conservador-TIJOLO | B3: Conservador | C3: TIJOLO | D3: 0.5 | E3: 0.0075 | G3: =G2+1 -> 1 | H3: =H2 * (1 + APP_INVEST!$D$23) + APP_INVEST!$D$22 -> 900 | I3: =I2 * (1 + APP_INVEST!$D$25) + APP_INVEST!$D$22 -> 900 | J3: =G3 * APP_INVEST!$D$22 -> 900 | K3: =J3 / (1 + APP_INVEST!$D$24)^G3 -> 897.06325
A4: =$B4&"-"&$C4 -> Conservador-HÍBRIDOS | B4: Conservador | C4: HÍBRIDOS | D4: 0.1 | E4: 0.0085 | G4: =G3+1 -> 2 | H4: =H3 * (1 + APP_INVEST!$D$23) + APP_INVEST!$D$22 -> 1808.4825 | I4: =I3 * (1 + APP_INVEST!$D$25) + APP_INVEST!$D$22 -> 1805.5181 | J4: =G4 * APP_INVEST!$D$22 -> 1800 | K4: =J4 / (1 + APP_INVEST!$D$24)^G4 -> 1788.2722
A5: =$B5&"-"&$C5 -> Conservador-FOFs | B5: Conservador | C5: FOFs | D5: 0.1 | E5: 0.008 | G5: =G4+1 -> 3 | H5: =H4 * (1 + APP_INVEST!$D$23) + APP_INVEST!$D$22 -> 2725.5274 | I5: =I4 * (1 + APP_INVEST!$D$25) + APP_INVEST!$D$22 -> 2716.588 | J5: =G5 * APP_INVEST!$D$22 -> 2700 | K5: =J5 / (1 + APP_INVEST!$D$24)^G5 -> 2673.6554
A6: =$B6&"-"&$C6 -> Conservador-DESENVOLVIMENTO | B6: Conservador | C6: DESENVOLVIMENTO | D6: 0 | E6: 0.012 | G6: =G5+1 -> 4 | H6: =H5 * (1 + APP_INVEST!$D$23) + APP_INVEST!$D$22 -> 3651.2155 | I6: =I5 * (1 + APP_INVEST!$D$25) + APP_INVEST!$D$22 -> 3633.244 | J6: =G6 * APP_INVEST!$D$22 -> 3600 | K6: =J6 / (1 + APP_INVEST!$D$24)^G6 -> 3553.2415
A7: =$B7&"-"&$C7 -> Conservador-HOTELARIAS | B7: Conservador | C7: HOTELARIAS | D7: 0 | E7: 0.01 | G7: =G6+1 -> 5 | H7: =H6 * (1 + APP_INVEST!$D$23) + APP_INVEST!$D$22 -> 4585.6283 | I7: =I6 * (1 + APP_INVEST!$D$25) + APP_INVEST!$D$22 -> 4555.5201 | J7: =G7 * APP_INVEST!$D$22 -> 4500 | K7: =J7 / (1 + APP_INVEST!$D$24)^G7 -> 4427.0588
A8: =$B8&"-"&$C8 -> Moderado-PAPEL | B8: Moderado | C8: PAPEL | D8: 0.32 | E8: 0.011 | G8: =G7+1 -> 6 | H8: =H7 * (1 + APP_INVEST!$D$23) + APP_INVEST!$D$22 -> 5528.8478 | I8: =I7 * (1 + APP_INVEST!$D$25) + APP_INVEST!$D$22 -> 5483.4508 | J8: =G8 * APP_INVEST!$D$22 -> 5400 | K8: =J8 / (1 + APP_INVEST!$D$24)^G8 -> 5295.1356
A9: =$B9&"-"&$C9 -> Moderado-TIJOLO | B9: Moderado | C9: TIJOLO | D9: 0.35 | E9: 0.0075 | G9: =G8+1 -> 7 | H9: =H8 * (1 + APP_INVEST!$D$23) + APP_INVEST!$D$22 -> 6480.9572 | I9: =I8 * (1 + APP_INVEST!$D$25) + APP_INVEST!$D$22 -> 6417.0709 | J9: =G9 * APP_INVEST!$D$22 -> 6300 | K9: =J9 / (1 + APP_INVEST!$D$24)^G9 -> 6157.5002
A10: =$B10&"-"&$C10 -> Moderado-HÍBRIDOS | B10: Moderado | C10: HÍBRIDOS | D10: 0.08 | E10: 0.0085 | G10: =G9+1 -> 8 | H10: =H9 * (1 + APP_INVEST!$D$23) + APP_INVEST!$D$22 -> 7442.0402 | I10: =I9 * (1 + APP_INVEST!$D$25) + APP_INVEST!$D$22 -> 7356.4151 | J10: =G10 * APP_INVEST!$D$22 -> 7200 | K10: =J10 / (1 + APP_INVEST!$D$24)^G10 -> 7014.1805
A11: =$B11&"-"&$C11 -> Moderado-FOFs | B11: Moderado | C11: FOFs | D11: 0.05 | E11: 0.008 | G11: =G10+1 -> 9 | H11: =H10 * (1 + APP_INVEST!$D$23) + APP_INVEST!$D$22 -> 8412.1814 | I11: =I10 * (1 + APP_INVEST!$D$25) + APP_INVEST!$D$22 -> 8301.5187 | J11: =G11 * APP_INVEST!$D$22 -> 8100 | K11: =J11 / (1 + APP_INVEST!$D$24)^G11 -> 7865.2044
A12: =$B12&"-"&$C12 -> Moderado-DESENVOLVIMENTO | B12: Moderado | C12: DESENVOLVIMENTO | D12: 0.1 | E12: 0.012 | G12: =G11+1 -> 10 | H12: =H11 * (1 + APP_INVEST!$D$23) + APP_INVEST!$D$22 -> 9391.4662 | I12: =I11 * (1 + APP_INVEST!$D$25) + APP_INVEST!$D$22 -> 9252.4169 | J12: =G12 * APP_INVEST!$D$22 -> 9000 | K12: =J12 / (1 + APP_INVEST!$D$24)^G12 -> 8710.5998
A13: =$B13&"-"&$C13 -> Moderado-HOTELARIAS | B13: Moderado | C13: HOTELARIAS | D13: 0.1 | E13: 0.01 | G13: =G12+1 -> 11 | H13: =H12 * (1 + APP_INVEST!$D$23) + APP_INVEST!$D$22 -> 10379.981 | I13: =I12 * (1 + APP_INVEST!$D$25) + APP_INVEST!$D$22 -> 10209.145 | J13: =G13 * APP_INVEST!$D$22 -> 9900 | K13: =J13 / (1 + APP_INVEST!$D$24)^G13 -> 9550.3943
A14: =$B14&"-"&$C14 -> Agressivo-PAPEL | B14: Agressivo | C14: PAPEL | D14: 0.4 | E14: 0.011 | G14: =G13+1 -> 12 | H14: =H13 * (1 + APP_INVEST!$D$23) + APP_INVEST!$D$22 -> 11377.812 | I14: =I13 * (1 + APP_INVEST!$D$25) + APP_INVEST!$D$22 -> 11171.739 | J14: =G14 * APP_INVEST!$D$22 -> 10800 | K14: =J14 / (1 + APP_INVEST!$D$24)^G14 -> 10384.615
... A19: =$B19&"-"&$C19 -> Agressivo-HOTELARIAS | B19: Agressivo | C19: HOTELARIAS | D19: 0.15 | E19: 0.01 | G19: =G18+1 -> 17 | H19: =H18 * (1 + APP_INVEST!$D$23) + APP_INVEST!$D$22 -> 16509.822 | I19: =I18 * (1 + APP_INVEST!$D$25) + APP_INVEST!$D$22 -> 16073.965 | J19: =G19 * APP_INVEST!$D$22 -> 15300 | K19: =J19 / (1 + APP_INVEST!$D$24)^G19 -> 14473.077
G20: =G19+1 -> 18 | H20: =H19 * (1 + APP_INVEST!$D$23) + APP_INVEST!$D$22 -> 17565.428 | I20: =I19 * (1 + APP_INVEST!$D$25) + APP_INVEST!$D$22 -> 17072.518 | J20: =G20 * APP_INVEST!$D$22 -> 16200 | K20: =J20 / (1 + APP_INVEST!$D$24)^G20 -> 15274.43
G21: =G20+1 -> 19 | H21: =H20 * (1 + APP_INVEST!$D$23) + APP_INVEST!$D$22 -> 18630.982 | I21: =I20 * (1 + APP_INVEST!$D$25) + APP_INVEST!$D$22 -> 18077.192 | J21: =G21 * APP_INVEST!$D$22 -> 17100 | K21: =J21 / (1 + APP_INVEST!$D$24)^G21 -> 16070.399
G22: =G21+1 -> 20 | H22: =H21 * (1 + APP_INVEST!$D$23) + APP_INVEST!$D$22 -> 19706.579 | I22: =I21 * (1 + APP_INVEST!$D$25) + APP_INVEST!$D$22 -> 19088.027 | J22: =G22 * APP_INVEST!$D$22 -> 18000 | K22: =J22 / (1 + APP_INVEST!$D$24)^G22 -> 16861.011
G23: =G22+1 -> 21 | H23: =H22 * (1 + APP_INVEST!$D$23) + APP_INVEST!$D$22 -> 20792.313 | I23: =I22 * (1 + APP_INVEST!$D$25) + APP_INVEST!$D$22 -> 20105.059 | J23: =G23 * APP_INVEST!$D$22 -> 18900 | K23: =J23 / (1 + APP_INVEST!$D$24)^G23 -> 17646.292
G24: =G23+1 -> 22 | H24: =H23 * (1 + APP_INVEST!$D$23) + APP_INVEST!$D$22 -> 21888.281 | I24: =I23 * (1 + APP_INVEST!$D$25) + APP_INVEST!$D$22 -> 21128.327 | J24: =G24 * APP_INVEST!$D$22 -> 19800 | K24: =J24 / (1 + APP_INVEST!$D$24)^G24 -> 18426.269
G25: =G24+1 -> 23 | H25: =H24 * (1 + APP_INVEST!$D$23) + APP_INVEST!$D$22 -> 22994.578 | I25: =I24 * (1 + APP_INVEST!$D$25) + APP_INVEST!$D$22 -> 22157.869 | J25: =G25 * APP_INVEST!$D$22 -> 20700 | K25: =J25 / (1 + APP_INVEST!$D$24)^G25 -> 19200.967
G26: =G25+1 -> 24 | H26: =H25 * (1 + APP_INVEST!$D$23) + APP_INVEST!$D$22 -> 24111.302 | I26: =I25 * (1 + APP_INVEST!$D$25) + APP_INVEST!$D$22 -> 23193.723 | J26: =G26 * APP_INVEST!$D$22 -> 21600 | K26: =J26 / (1 + APP_INVEST!$D$24)^G26 -> 19970.414
G27: =G26+1 -> 25 | H27: =H26 * (1 + APP_INVEST!$D$23) + APP_INVEST!$D$22 -> 25238.551 | I27: =I26 * (1 + APP_INVEST!$D$25) + APP_INVEST!$D$22 -> 24235.928 | J27: =G27 * APP_INVEST!$D$22 -> 22500 | K27: =J27 / (1 + APP_INVEST!$D$24)^G27 -> 20734.635
G28: =G27+1 -> 26 | H28: =H27 * (1 + APP_INVEST!$D$23) + APP_INVEST!$D$22 -> 26376.424 | I28: =I27 * (1 + APP_INVEST!$D$25) + APP_INVEST!$D$22 -> 25284.523 | J28: =G28 * APP_INVEST!$D$22 -> 23400 | K28: =J28 / (1 + APP_INVEST!$D$24)^G28 -> 21493.656
G29: =G28+1 -> 27 | H29: =H28 * (1 + APP_INVEST!$D$23) + APP_INVEST!$D$22 -> 27525.022 | I29: =I28 * (1 + APP_INVEST!$D$25) + APP_INVEST!$D$22 -> 26339.547 | J29: =G29 * APP_INVEST!$D$22 -> 24300 | K29: =J29 / (1 + APP_INVEST!$D$24)^G29 -> 22247.502
G30: =G29+1 -> 28 | H30: =H29 * (1 + APP_INVEST!$D$23) + APP_INVEST!$D$22 -> 28684.445 | I30: =I29 * (1 + APP_INVEST!$D$25) + APP_INVEST!$D$22 -> 27401.04 | J30: =G30 * APP_INVEST!$D$22 -> 25200 | K30: =J30 / (1 + APP_INVEST!$D$24)^G30 -> 22996.2
G31: =G30+1 -> 29 | H31: =H30 * (1 + APP_INVEST!$D$23) + APP_INVEST!$D$22 -> 29854.796 | I31: =I30 * (1 + APP_INVEST!$D$25) + APP_INVEST!$D$22 -> 28469.041 | J31: =G31 * APP_INVEST!$D$22 -> 26100 | K31: =J31 / (1 + APP_INVEST!$D$24)^G31 -> 23739.775
... G362: =G361+1 -> 360 | H362: =H361 * (1 + APP_INVEST!$D$23) + APP_INVEST!$D$22 -> 2701052.3 | I362: =I361 * (1 + APP_INVEST!$D$25) + APP_INVEST!$D$22 -> 1178643.3 | J362: =G362 * APP_INVEST!$D$22 -> 324000 | K362: =J362 / (1 + APP_INVEST!$D$24)^G362 -> 99895.248
